Metadata-Version: 2.1
Name: clubhouse-py
Version: 434.0.1
Summary: Clubhouse API written in Python. Standalone client included.For reference and education purposes only.
Home-page: https://github.com/stypr/clubhouse-py
Author: Harold Kim
Author-email: root@stypr.com
License: MIT
Download-URL: https://github.com/stypr/clubhouse-py/archive/v434.0.1.tar.gz
Keywords: clubhouse,voice-chat,clubhouse-client,clubhouse-api,clubhouse-lib
Platform: UNKNOWN
Classifier: Development Status :: 5 - Production/Stable
Classifier: Intended Audience :: Developers
Classifier: License :: OSI Approved :: MIT License
Classifier: Operating System :: MacOS
Classifier: Operating System :: Microsoft :: Windows :: Windows 10
Classifier: Programming Language :: Python :: 3
Classifier: Programming Language :: Python :: 3.7
Classifier: Programming Language :: Python :: 3.8
Classifier: Programming Language :: Python :: 3.9
